Metadata-Version: 1.0
Name: jsonpull
Version: 0.1.0
Summary: create a formatted string of the Python JSON object
Home-page: https://github.com/majidazizian/jsonpull
Author: Majid Azizian
Author-email: your.email@domain.com
License: MIT
Platform: UNKNOWN
